[
  {
    "id": "dc006d67-4cb6-4b5b-9782-6dc3eee5ba12",
    "tagname": "ajax",
    "description": "AJAX (Asynchronous JavaScript and XML) is a technique for creating interactive website user interfaces without the traditional web page refresh or reload. It uses asynchronous data exchange between client and server to update displayed information and respond to user interactions seamlessly. Include additional tags for programming languages, libraries, frameworks, web browser, protocols and other environmental information.",
    "posts_count": 15,
    "created_at": "2022-03-05T09:53:57.000Z"
  },
  {
    "id": "31ad4468-52d8-48e9-bc4e-0c564ec30fca",
    "tagname": "React",
    "description": "A React is a keyword or term assigned to a piece of information",
    "posts_count": 8,
    "created_at": "2022-03-19T17:47:31.000Z"
  },
  {
    "id": "4d1bcc7d-1175-47b0-857a-91997893984a",
    "tagname": "test",
    "description": "A test is a keyword or term assigned to a piece of information",
    "posts_count": 6,
    "created_at": "2022-03-10T11:28:15.000Z"
  },
  {
    "id": "8a913ea9-eea1-40e0-94f7-e489a2167448",
    "tagname": "java",
    "description": "Java is a high-level object oriented programming language. Use this tag when you&#39;re having problems using or understanding the language itself. This tag is frequently used alongside other tags for libraries and/or frameworks used by Java developers.",
    "posts_count": 6,
    "created_at": "2022-03-05T09:53:53.000Z"
  },
  {
    "id": "088ce98e-7ac9-41ca-b1b7-a3e22d7430d6",
    "tagname": "django",
    "description": "Django is an open-source server-side web application framework written in Python. It is designed to reduce the effort required to create complex data-driven websites and web applications, with a special focus on less code, no-redundancy and being more explicit than implicit.",
    "posts_count": 5,
    "created_at": "2022-03-30T14:39:14.000Z"
  },
  {
    "id": "ab0b6dae-9b90-4541-932e-c929a3056d0d",
    "tagname": "reactjs",
    "description": "React is a JavaScript library for building user interfaces. It uses a declarative, component-based paradigm and aims to be both efficient and flexible.",
    "posts_count": 4,
    "created_at": "2022-03-01T17:24:10.000Z"
  },
  {
    "id": "c19291fd-0a49-460c-8495-21e107b36c9f",
    "tagname": "javascript",
    "description": "For questions regarding programming in ECMAScript (JavaScript/JS) and its various dialects/implementations (excluding ActionScript). Note JavaScript is NOT the same as Java! Please include all relevant tags on your question; e.g., [node.js], [jquery], [json], [reactjs], [angular], [ember.js], [vue.js], [typescript], [svelte], etc.",
    "posts_count": 4,
    "created_at": "2022-03-03T18:48:47.000Z"
  },
  {
    "id": "acef49b0-2e0c-47c5-92dc-7b98a75fd01a",
    "tagname": "python",
    "description": "Python is a multi-paradigm, dynamically typed, multi-purpose programming language. It is designed to be quick to learn, understand, and use, and enforces a clean and uniform syntax. Please note that Python 2 is officially out of support as of 2020-01-01. For version-specific Python questions, add the [python-2.7] or [python-3.x] tag. When using a Python variant (e.g. Jython, PyPy) or library (e.g. Pandas, NumPy), please include it in the tags.",
    "posts_count": 3,
    "created_at": "2022-04-05T18:36:54.000Z"
  },
  {
    "id": "fc4dfdb9-4cc8-4791-8242-b11d4784bc89",
    "tagname": "mysql",
    "description": "MySQL is a free, open source Relational Database Management System (RDBMS) that uses Structured Query Language (SQL).",
    "posts_count": 3,
    "created_at": "2022-02-27T17:59:40.000Z"
  },
  {
    "id": "0506e0b7-8b84-4565-bf19-e3e9619891cf",
    "tagname": "js",
    "description": "A js is a keyword or term assigned to a piece of information",
    "posts_count": 2,
    "created_at": "2022-07-16T05:05:16.000Z"
  },
  {
    "id": "0cbb9a18-10a3-4463-a2ef-f51a92f7a496",
    "tagname": "mongodb",
    "description": "MongoDB is a scalable, high-performance, open source, document-oriented NoSQL database. It supports a large number of languages and application development platforms. Questions about server administration can be asked on https://dba.stackexchange.com.",
    "posts_count": 2,
    "created_at": "2022-06-24T02:39:22.000Z"
  },
  {
    "id": "233c64d6-eabb-4296-acbf-0184fb7d766a",
    "tagname": "mongoose",
    "description": "Mongoose is a MongoDB object modeling tool, or ODM (Object Document Mapper), written in JavaScript and designed to work in an asynchronous environment.",
    "posts_count": 2,
    "created_at": "2022-06-24T02:39:22.000Z"
  },
  {
    "id": "5d87425e-b520-4c1d-bfa0-834f4dc69935",
    "tagname": "php",
    "description": "PHP is a widely used, open source, general-purpose, multi-paradigm, dynamically typed and interpreted scripting language originally designed for server-side web development. Use this tag for questions about programming in the PHP language.",
    "posts_count": 2,
    "created_at": "2022-07-16T19:54:58.000Z"
  },
  {
    "id": "82117396-ca08-48f2-b6ab-8f67db336cf6",
    "tagname": "sorting",
    "description": "Sorting is the process of applying some order to a collection of items.",
    "posts_count": 2,
    "created_at": "2022-10-03T10:16:29.000Z"
  },
  {
    "id": "92799983-deb7-4532-9efd-27903ea6ff80",
    "tagname": "html",
    "description": "HTML (HyperText Markup Language) is the markup language for creating web pages and other information to be displayed in a web browser. Questions regarding HTML should include a minimal reproducible example and some idea of what you&#39;re trying to achieve. This tag is rarely used alone and is often paired with [CSS] and [JavaScript].",
    "posts_count": 2,
    "created_at": "2022-03-05T09:53:50.000Z"
  },
  {
    "id": "f12a2e83-3436-4052-a5c2-573639810bb6",
    "tagname": "mern",
    "description": "MERN stands for Mongo, Express, React and NodeJS.\r\n\r\n",
    "posts_count": 2,
    "created_at": "2022-04-09T10:50:57.000Z"
  },
  {
    "id": "fc1466a1-d3c7-4ebf-a070-5a0481987886",
    "tagname": "question",
    "description": "A question is a keyword or term assigned to a piece of information",
    "posts_count": 2,
    "created_at": "2022-04-09T10:50:08.000Z"
  },
  {
    "id": "011a6057-20eb-4086-9395-27f5c05cc3ff",
    "tagname": "mern react",
    "description": "A mern react is a keyword or term assigned to a piece of information",
    "posts_count": 1,
    "created_at": "2022-06-16T06:38:28.000Z"
  },
  {
    "id": "068332c9-3899-4c62-b353-0dc9e153ebd0",
    "tagname": "Huehue",
    "description": "A Huehue is a keyword or term assigned to a piece of information",
    "posts_count": 1,
    "created_at": "2022-03-13T19:39:24.000Z"
  },
  {
    "id": "07031704-10d8-45f5-8b09-03a77b400fc7",
    "tagname": "online",
    "description": "A online is a keyword or term assigned to a piece of information",
    "posts_count": 1,
    "created_at": "2022-07-11T06:06:33.000Z"
  },
  {
    "id": "072ce50d-5505-4371-b09b-7efabd6e599f",
    "tagname": "Group",
    "description": "A Group is a keyword or term assigned to a piece of information",
    "posts_count": 1,
    "created_at": "2022-08-15T11:25:03.000Z"
  },
  {
    "id": "09b78fa9-faf4-4808-9f3e-1c6813c546ab",
    "tagname": "thx",
    "description": "A thx is a keyword or term assigned to a piece of information",
    "posts_count": 1,
    "created_at": "2022-03-03T14:32:39.000Z"
  },
  {
    "id": "0b306def-9fad-44f7-81e2-126e06a9c9ef",
    "tagname": "qweqweqweqwe",
    "description": "A qweqweqweqwe is a keyword or term assigned to a piece of information",
    "posts_count": 1,
    "created_at": "2022-04-06T16:25:22.000Z"
  },
  {
    "id": "0c9fc190-5357-4630-9ea7-68cd4c098fc8",
    "tagname": "material-ui",
    "description": "React components that implement Google&#39;s Material Design. Please note that this tag should be used for questions regarding the MUI (formerly Material-UI) library. Otherwise, see the tag&#39;s info for other tags to use.",
    "posts_count": 1,
    "created_at": "2022-03-05T17:09:51.000Z"
  },
  {
    "id": "0d07349c-79b2-445c-8e1d-77d1c9ac7905",
    "tagname": "gsg",
    "description": "A gsg is a keyword or term assigned to a piece of information",
    "posts_count": 1,
    "created_at": "2022-03-10T11:11:53.000Z"
  },
  {
    "id": "15eb62c0-bf3a-4980-9daa-f4a26bcb4ae3",
    "tagname": "asdfdsfds",
    "description": "A asdfdsfds is a keyword or term assigned to a piece of information",
    "posts_count": 1,
    "created_at": "2022-06-17T02:43:24.000Z"
  },
  {
    "id": "1762d8a5-dbd3-4138-88a6-c4f8dedb5035",
    "tagname": "",
    "description": "A  is a keyword or term assigned to a piece of information",
    "posts_count": 1,
    "created_at": "2022-07-03T21:46:56.000Z"
  },
  {
    "id": "17bf850f-de7c-4984-bc6d-ce6094643167",
    "tagname": "Hehe",
    "description": "A Hehe is a keyword or term assigned to a piece of information",
    "posts_count": 1,
    "created_at": "2022-03-13T19:41:36.000Z"
  },
  {
    "id": "1b25b14b-0e28-4379-bb1b-479c9706ae77",
    "tagname": "Chinese language",
    "description": "A Chinese language is a keyword or term assigned to a piece of information",
    "posts_count": 1,
    "created_at": "2022-06-24T06:49:11.000Z"
  },
  {
    "id": "1dd22177-93d2-417f-bfa4-5c0fd61a8071",
    "tagname": "@test",
    "description": "A @test is a keyword or term assigned to a piece of information",
    "posts_count": 1,
    "created_at": "2022-05-02T04:04:46.000Z"
  },
  {
    "id": "1ee357c9-65bc-4b55-82c1-4162c6184b46",
    "tagname": "cleanse",
    "description": "Questions pertaining to Square&#39;s Cleanse Dependency Injection Framework for Swift",
    "posts_count": 1,
    "created_at": "2022-03-18T17:58:36.000Z"
  },
  {
    "id": "2287312d-8bb3-4bfd-8f3e-2911d391839f",
    "tagname": "redis",
    "description": "Redis is an open source (BSD licensed), in-memory data structure store, used as a database, cache and message broker. It supports data structures such as strings, hashes, lists, sets, sorted sets with range queries, bitmaps, hyperloglogs, geospatial indexes with radius queries and streams. It also provides pub-sub capabilities. Use this tag for questions related to Redis and in-memory system.",
    "posts_count": 1,
    "created_at": "2022-09-29T17:49:42.000Z"
  },
  {
    "id": "235d00a8-b83c-4d71-a929-5ca51ecbac44",
    "tagname": "Test Hello",
    "description": "A Test Hello is a keyword or term assigned to a piece of information",
    "posts_count": 1,
    "created_at": "2022-07-04T05:45:40.000Z"
  },
  {
    "id": "23ae83bb-7198-49bf-9352-99b7da3faf74",
    "tagname": "sas",
    "description": "The SAS language is a 4GL that underpins the SAS system, a suite of products centered around data processing and statistical procedures.  For questions about code, please include your code and some data to reproduce your problem, either in datalines/cards statements or using a sashelp dataset like sashelp.class or sashelp.cars.",
    "posts_count": 1,
    "created_at": "2022-05-16T13:45:18.000Z"
  },
  {
    "id": "32841ac4-dcf0-4444-92ee-51b019a65189",
    "tagname": "adf asdf asdf",
    "description": "A adf asdf asdf is a keyword or term assigned to a piece of information",
    "posts_count": 1,
    "created_at": "2022-03-03T07:29:52.000Z"
  },
  {
    "id": "35165dd3-e090-491f-a334-ed526f3a469c",
    "tagname": "jquery",
    "description": "jQuery is a JavaScript library, consider also adding the JavaScript tag. \r\n\r\njQuery is a popular cross-browser JavaScript library that facilitates Document Object Model (DOM) traversal, event handling, animations and AJAX interactions by minimizing the discrepancies across browsers. A question tagged jQuery should be related to jQuery, so jQuery should be used by the code in question and at least jQuery usage-related elements need to be in the question.",
    "posts_count": 1,
    "created_at": "2022-06-13T06:59:28.000Z"
  },
  {
    "id": "35c9b1d0-d9c3-4e8d-b5fa-600906cc4994",
    "tagname": "nodejs",
    "description": "A nodejs is a keyword or term assigned to a piece of information",
    "posts_count": 1,
    "created_at": "2022-06-24T02:39:22.000Z"
  },
  {
    "id": "38dffb62-f4a8-4be6-9d40-37d9f845585c",
    "tagname": "mangodb",
    "description": "A mangodb is a keyword or term assigned to a piece of information",
    "posts_count": 1,
    "created_at": "2022-06-24T06:55:09.000Z"
  },
  {
    "id": "3e7c5b2c-6cbd-4454-acb5-4b924c09f034",
    "tagname": "test mern stack dev",
    "description": "A test mern stack dev is a keyword or term assigned to a piece of information",
    "posts_count": 1,
    "created_at": "2022-03-23T19:48:57.000Z"
  },
  {
    "id": "4081da27-8811-46df-9e8d-6eadde687b04",
    "tagname": "json",
    "description": "JSON (JavaScript Object Notation) is a serializable data interchange format intended to be machine and human readable. Do not use this tag for native JavaScript objects or JavaScript object literals. Before you ask a question, validate your JSON using a JSON validator such as JSONLint (https://jsonlint.com).",
    "posts_count": 1,
    "created_at": "2022-06-23T18:06:54.000Z"
  },
  {
    "id": "415f2155-fcf0-463e-ba16-87434d6ad10b",
    "tagname": "node.js",
    "description": "Node.js is an event-based, non-blocking, asynchronous I/O runtime that uses Google&#39;s V8 JavaScript engine and libuv library. It is used for developing applications that make heavy use of the ability to run JavaScript both on the client, as well as on server side and therefore benefit from the re-usability of code and the lack of context switching.",
    "posts_count": 1,
    "created_at": "2022-03-05T17:43:14.000Z"
  },
  {
    "id": "44ca9078-166f-4ae1-bdd0-f846946ca578",
    "tagname": "fuck",
    "description": "A fuck is a keyword or term assigned to a piece of information",
    "posts_count": 1,
    "created_at": "2022-05-22T10:21:11.000Z"
  },
  {
    "id": "48d4ec0e-dadd-45c6-a842-3dc57f4d6a1f",
    "tagname": "111111111111111111111111111111111111111111111111111111",
    "description": "A 111111111111111111111111111111111111111111111111111111 is a keyword or term assigned to a piece of information",
    "posts_count": 1,
    "created_at": "2022-04-15T09:28:27.000Z"
  },
  {
    "id": "4a991d0c-c4a3-4780-a728-4870242c33c4",
    "tagname": "Enter a title with minimum 15 characters",
    "description": "A Enter a title with minimum 15 characters is a keyword or term assigned to a piece of information",
    "posts_count": 1,
    "created_at": "2022-06-23T09:51:06.000Z"
  },
  {
    "id": "4dc15ac7-03d6-49ee-a0f3-42fb8d65c693",
    "tagname": "sadsad",
    "description": "A sadsad is a keyword or term assigned to a piece of information",
    "posts_count": 1,
    "created_at": "2022-06-25T11:09:55.000Z"
  },
  {
    "id": "537c79e0-6631-43a2-9e2a-a827e1ad2767",
    "tagname": "css",
    "description": "CSS (Cascading Style Sheets) is a representation style sheet language used for describing the look and formatting of HTML (HyperText Markup Language), XML (Extensible Markup Language) documents and SVG elements including (but not limited to) colors, layout, fonts, and animations. It also describes how elements should be rendered on screen, on paper, in speech, or on other media.",
    "posts_count": 1,
    "created_at": "2022-03-05T09:53:47.000Z"
  },
  {
    "id": "5d48368b-1607-4835-b5b2-630eb3122042",
    "tagname": "aseasegasegaseg",
    "description": "A aseasegasegaseg is a keyword or term assigned to a piece of information",
    "posts_count": 1,
    "created_at": "2022-08-26T04:30:31.000Z"
  },
  {
    "id": "5da3b5f2-5b84-4f7e-9ff5-0193b9cb6530",
    "tagname": "capital",
    "description": "A capital is a keyword or term assigned to a piece of information",
    "posts_count": 1,
    "created_at": "2022-10-06T13:38:35.000Z"
  },
  {
    "id": "642a23a5-6821-4b24-9863-cde8fdf0869b",
    "tagname": "intellij-idea",
    "description": "IntelliJ IDEA is an IDE by JetBrains. It primarily supports Java development, but also supports JavaScript, Groovy, HTML, CSS, RSS, R, Haskell, PHP, Ruby, Python, Scala, Swift, Clojure, Kotlin, Hybris, Gradle and others. Questions specifically concerning usage and problems in both Community and Ultimate Editions should use this tag. However, if you have a problem with something else and just happen to be using IntelliJ, please don&#39;t use this tag.",
    "posts_count": 1,
    "created_at": "2022-03-03T17:48:11.000Z"
  },
  {
    "id": "643c5e87-a3bb-45ce-b6d1-7ca7154726c1",
    "tagname": "AAAAAAAAAAAAAAAAAAAA",
    "description": "A AAAAAAAAAAAAAAAAAAAA is a keyword or term assigned to a piece of information",
    "posts_count": 1,
    "created_at": "2022-04-17T14:44:53.000Z"
  },
  {
    "id": "6710534f-abe3-4514-a831-ba059857c640",
    "tagname": "lol code nice",
    "description": "A lol code nice is a keyword or term assigned to a piece of information",
    "posts_count": 1,
    "created_at": "2022-06-23T22:50:17.000Z"
  },
  {
    "id": "6b2b8acc-1f30-4080-a08e-90cf9e0403df",
    "tagname": "wwwed",
    "description": "A wwwed is a keyword or term assigned to a piece of information",
    "posts_count": 1,
    "created_at": "2022-04-07T21:36:58.000Z"
  },
  {
    "id": "6be0809d-7a68-43ef-8bad-2a0d3742ad8c",
    "tagname": "testtagnam",
    "description": "A testtagnam is a keyword or term assigned to a piece of information",
    "posts_count": 1,
    "created_at": "2022-08-02T11:14:46.000Z"
  },
  {
    "id": "71ad1f92-f424-4cae-a1ec-3558ac6a860f",
    "tagname": "general",
    "description": "A general is a keyword or term assigned to a piece of information",
    "posts_count": 1,
    "created_at": "2022-06-30T18:58:09.000Z"
  },
  {
    "id": "7a02d73f-2101-4924-9512-6aa73bdba686",
    "tagname": "aa",
    "description": "A aa is a keyword or term assigned to a piece of information",
    "posts_count": 1,
    "created_at": "2022-04-05T17:22:58.000Z"
  },
  {
    "id": "7a3595ce-f91f-4d74-bfdf-203bd6e1d0bb",
    "tagname": "goodjob",
    "description": "A goodjob is a keyword or term assigned to a piece of information",
    "posts_count": 1,
    "created_at": "2022-03-10T11:13:51.000Z"
  },
  {
    "id": "7e96e245-529e-43c2-bb15-0db1de8244cf",
    "tagname": "excel-formula",
    "description": "This tag is for Microsoft Excel questions where the question or answers are specifically about the structure, syntax, or output of an Excel formula.",
    "posts_count": 1,
    "created_at": "2022-03-18T17:58:36.000Z"
  },
  {
    "id": "7fc1a046-9218-4523-8f25-ac7c4d98623a",
    "tagname": "fsdsdfsdf",
    "description": "A fsdsdfsdf is a keyword or term assigned to a piece of information",
    "posts_count": 1,
    "created_at": "2022-05-22T09:58:47.000Z"
  },
  {
    "id": "810d6634-7263-4e56-9d8c-67d1ee3ed1fc",
    "tagname": "data-cleaning",
    "description": "Data cleaning is the process of removing or repairing errors, and normalizing data used in computer programs.  For example, outliers may be removed, missing samples may be interpolated, invalid values may be marked as unavailable, and synonymous values may be merged.\r\nOne approach to data cleaning is the &quot;tidy data&quot; framework from Wickham, which means each row is an observation and each column is a variable.",
    "posts_count": 1,
    "created_at": "2022-03-18T17:58:36.000Z"
  },
  {
    "id": "85776542-385a-4555-b06f-e36d1990b84d",
    "tagname": "difference",
    "description": "This tag may refer to 1) the difference between two numbers (i.e. the difference between 5 and 10 is 5) or 2) the things that two or more particular objects do not share in common.",
    "posts_count": 1,
    "created_at": "2022-08-19T15:30:57.000Z"
  },
  {
    "id": "898aec46-ab56-469a-a8ee-f71567dd4156",
    "tagname": "excel",
    "description": "Only for questions on programming against Excel objects or files, or complex formula development. You may combine the Excel tag with VBA, VSTO, C#, VB.NET, PowerShell, OLE automation, and other programming related tags and questions if applicable.\r\n\r\nGeneral help regarding Excel for single worksheet functions is available at Super User (http://superuser.com/).",
    "posts_count": 1,
    "created_at": "2022-03-18T17:58:36.000Z"
  },
  {
    "id": "8e487a06-adfb-4bfa-8765-d14d9a2266d8",
    "tagname": "heg",
    "description": "A heg is a keyword or term assigned to a piece of information",
    "posts_count": 1,
    "created_at": "2022-03-02T03:34:30.000Z"
  },
  {
    "id": "9640f207-e3d1-4282-9303-f67d9c366ffa",
    "tagname": "orm",
    "description": "Object-relational mapping (ORM) is a technique for mapping object-oriented systems to relational databases. Use other tags to indicate the programming language ([java], [sql], [python]), database system ([postgreSQL], content management system ([django]), framework ([flask], [spring], [laravel]), application environment ([android], [node.js]), and other tags that can be used for searches and have watchers.",
    "posts_count": 1,
    "created_at": "2022-03-05T17:43:16.000Z"
  },
  {
    "id": "9a6d9d66-fd65-4be7-8f1b-3db16d062cf2",
    "tagname": "micros",
    "description": "A micros is a keyword or term assigned to a piece of information",
    "posts_count": 1,
    "created_at": "2022-09-29T17:42:22.000Z"
  },
  {
    "id": "9d857866-6f95-4686-8a60-875a4e13ef8e",
    "tagname": "hhh",
    "description": "A hhh is a keyword or term assigned to a piece of information",
    "posts_count": 1,
    "created_at": "2022-10-15T00:50:42.000Z"
  },
  {
    "id": "9ff65846-2ccd-4606-8b69-006b3dad190e",
    "tagname": "helpit",
    "description": "A helpit is a keyword or term assigned to a piece of information",
    "posts_count": 1,
    "created_at": "2022-09-29T05:10:11.000Z"
  },
  {
    "id": "a7f6061d-c0ad-4218-baa2-82f0423bac93",
    "tagname": "appbar",
    "description": "An application desktop toolbar (also called an appbar) is a window that is similar to the Windows taskbar.",
    "posts_count": 1,
    "created_at": "2022-03-05T17:09:54.000Z"
  },
  {
    "id": "accb9f5c-fb77-4029-8150-209fb5f6c076",
    "tagname": "trial",
    "description": "A trial is a keyword or term assigned to a piece of information",
    "posts_count": 1,
    "created_at": "2022-10-19T07:29:48.000Z"
  },
  {
    "id": "b2700531-9195-41ef-8715-7305917288a6",
    "tagname": "node",
    "description": "A node is a keyword or term assigned to a piece of information",
    "posts_count": 1,
    "created_at": "2022-09-04T11:09:13.000Z"
  },
  {
    "id": "b372e8e5-a509-4c42-9fd8-0184cf847be1",
    "tagname": "testtagname",
    "description": "A testtagname is a keyword or term assigned to a piece of information",
    "posts_count": 1,
    "created_at": "2022-08-02T11:14:46.000Z"
  },
  {
    "id": "b5f7e74d-ef4c-43da-b00f-5cb0d7d50919",
    "tagname": "htmlcss",
    "description": "A htmlcss is a keyword or term assigned to a piece of information",
    "posts_count": 1,
    "created_at": "2022-07-16T05:05:16.000Z"
  },
  {
    "id": "b6261e73-b94b-4e7b-bb3b-b5167c51a013",
    "tagname": "webstorm",
    "description": "WebStorm is a commercial IDE built by JetBrains for editing JavaScript, HTML, and CSS. It is built on the IntelliJ IDEA platform.",
    "posts_count": 1,
    "created_at": "2022-03-03T17:45:09.000Z"
  },
  {
    "id": "b65e2bbd-82e5-4a96-b858-19ffcf63bcc0",
    "tagname": "draftjs",
    "description": "Draft.js is a framework for building rich text editors in React, powered by an immutable model and abstracting over cross-browser differences.",
    "posts_count": 1,
    "created_at": "2022-06-30T18:57:04.000Z"
  },
  {
    "id": "b769dfe6-c7f8-419e-8aac-cf783fda52a1",
    "tagname": "regex",
    "description": "Regular expressions provide a declarative language to match patterns within strings. They are commonly used for string validation, parsing, and transformation. Because regular expressions are not fully standardized, all questions with this tag should also include a tag specifying the applicable programming language or tool. Do not post questions asking for an explanation of what a symbol means or what a particular regular expression will match.",
    "posts_count": 1,
    "created_at": "2022-03-18T14:05:53.000Z"
  },
  {
    "id": "bd499281-2a59-4883-a561-62d23bb90923",
    "tagname": "strung",
    "description": "A strung is a keyword or term assigned to a piece of information",
    "posts_count": 1,
    "created_at": "2022-03-13T04:54:11.000Z"
  },
  {
    "id": "c4f73da7-d41b-4fa0-83f9-b75be1617d20",
    "tagname": "sequelize.js",
    "description": "The Sequelize library provides an ORM (Object-Relational-Mapper) for Node.js, written entirely in JavaScript. Provides easy mapping for MySQL, MariaDB, SQLite, PostgreSQL and SQL Server.",
    "posts_count": 1,
    "created_at": "2022-03-05T17:43:17.000Z"
  },
  {
    "id": "c6839536-3321-49a3-b831-736902e5b582",
    "tagname": "testtagna",
    "description": "A testtagna is a keyword or term assigned to a piece of information",
    "posts_count": 1,
    "created_at": "2022-08-02T11:14:46.000Z"
  },
  {
    "id": "cb21be48-949f-46ea-8ee8-ce07cd22062c",
    "tagname": "cvbcvcv",
    "description": "A cvbcvcv is a keyword or term assigned to a piece of information",
    "posts_count": 1,
    "created_at": "2022-08-24T05:59:57.000Z"
  },
  {
    "id": "cbd4114f-2443-4681-89e4-087f35a22797",
    "tagname": "penis",
    "description": "A penis is a keyword or term assigned to a piece of information",
    "posts_count": 1,
    "created_at": "2022-03-13T16:08:41.000Z"
  },
  {
    "id": "cf631482-ad3c-4f74-9952-13248bc1d597",
    "tagname": "hhhhhhhhhhhhhhhhhhhhhhhhhhhhhhhhhhhhhhhhhhhhhhhhhh",
    "description": "A hhhhhhhhhhhhhhhhhhhhhhhhhhhhhhhhhhhhhhhhhhhhhhhhhh is a keyword or term assigned to a piece of information",
    "posts_count": 1,
    "created_at": "2022-06-17T01:47:08.000Z"
  },
  {
    "id": "d16abbcb-369d-416a-8a12-379a3abd01f0",
    "tagname": "Filters Question",
    "description": "A Filters Question is a keyword or term assigned to a piece of information",
    "posts_count": 1,
    "created_at": "2022-07-07T03:30:04.000Z"
  },
  {
    "id": "d5fa0ea6-f98e-4807-ae50-e3b7a27a9e58",
    "tagname": "javascriptpt",
    "description": "A javascriptpt is a keyword or term assigned to a piece of information",
    "posts_count": 1,
    "created_at": "2022-03-15T18:06:44.000Z"
  },
  {
    "id": "d8495d4b-c75f-45bd-bff4-57b83b294d03",
    "tagname": "hacktoberfest",
    "description": "A hacktoberfest is a keyword or term assigned to a piece of information",
    "posts_count": 1,
    "created_at": "2022-10-03T07:37:18.000Z"
  },
  {
    "id": "e8dbcc68-b3f5-4a33-bb64-1dfa4840f97f",
    "tagname": "unnecessarilyLongTagBeingAddedWhichIsWrong",
    "description": "A unnecessarilyLongTagBeingAddedWhichIsWrong is a keyword or term assigned to a piece of information",
    "posts_count": 1,
    "created_at": "2022-07-03T18:06:43.000Z"
  },
  {
    "id": "ed6d4cf7-eb6f-46e2-9e25-e76d3c3c720b",
    "tagname": "fffffff",
    "description": "A fffffff is a keyword or term assigned to a piece of information",
    "posts_count": 1,
    "created_at": "2022-07-08T09:49:04.000Z"
  },
  {
    "id": "f24a4d59-a49a-469f-829d-52937d237dbe",
    "tagname": "哇的 我的 我的",
    "description": "A 哇的 我的 我的 is a keyword or term assigned to a piece of information",
    "posts_count": 1,
    "created_at": "2022-03-03T07:29:17.000Z"
  },
  {
    "id": "005ee9cb-b0b3-4599-8294-696519d545a1",
    "tagname": "lodash",
    "description": "A modern JavaScript utility library delivering modularity, performance, and extras.",
    "posts_count": 0,
    "created_at": "2022-03-05T17:50:08.000Z"
  },
  {
    "id": "041bdb6f-a981-43e4-b5a7-56f46c83c7d0",
    "tagname": "soine",
    "description": "A soine is a keyword or term assigned to a piece of information",
    "posts_count": 0,
    "created_at": "2022-07-03T21:46:56.000Z"
  },
  {
    "id": "054535ac-dd76-437d-986f-51f7357698c2",
    "tagname": "string",
    "description": "A string is a finite sequence of symbols, commonly used for text, though sometimes for arbitrary data.",
    "posts_count": 0,
    "created_at": "2022-03-03T19:06:27.000Z"
  },
  {
    "id": "1bb96c9b-93b2-40fe-95c0-c3bdfebc4b08",
    "tagname": "nave",
    "description": "A nave is a keyword or term assigned to a piece of information",
    "posts_count": 0,
    "created_at": "2022-07-03T20:47:28.000Z"
  },
  {
    "id": "339f02ef-7fca-472a-93c2-93e959c80ab6",
    "tagname": "ouououo",
    "description": "A ouououo is a keyword or term assigned to a piece of information",
    "posts_count": 0,
    "created_at": "2022-05-09T15:57:17.000Z"
  },
  {
    "id": "3462348a-325d-42b6-b155-6eff12e13eb0",
    "tagname": "some",
    "description": "A some is a keyword or term assigned to a piece of information",
    "posts_count": 0,
    "created_at": "2022-07-03T22:03:47.000Z"
  },
  {
    "id": "3be25740-9454-433b-9997-303c40fe3fb3",
    "tagname": "unnecessarilyLongTa",
    "description": "A unnecessarilyLongTa is a keyword or term assigned to a piece of information",
    "posts_count": 0,
    "created_at": "2022-07-03T21:56:16.000Z"
  },
  {
    "id": "52a57cec-e348-491e-b780-d3c64a7a2264",
    "tagname": "clean",
    "description": "A clean is a keyword or term assigned to a piece of information",
    "posts_count": 0,
    "created_at": "2022-07-04T21:42:18.000Z"
  },
  {
    "id": "52b63212-3d31-48a5-beab-5532b8e6e4d7",
    "tagname": "sine",
    "description": "A sine is a keyword or term assigned to a piece of information",
    "posts_count": 0,
    "created_at": "2022-07-03T22:05:07.000Z"
  },
  {
    "id": "627ed2e8-c523-4b5d-88cb-e46f22b06712",
    "tagname": "ajaz2df",
    "description": "A ajaz2df is a keyword or term assigned to a piece of information",
    "posts_count": 0,
    "created_at": "2022-07-03T22:03:05.000Z"
  },
  {
    "id": "638958ea-79e5-4e40-997b-da7a7ed9b114",
    "tagname": "havasc",
    "description": "A havasc is a keyword or term assigned to a piece of information",
    "posts_count": 0,
    "created_at": "2022-07-03T20:47:28.000Z"
  },
  {
    "id": "6e262883-7a6f-4a92-8ea4-f38fe81b252e",
    "tagname": "adjksajkjvkg",
    "description": "A adjksajkjvkg is a keyword or term assigned to a piece of information",
    "posts_count": 0,
    "created_at": "2022-07-03T21:56:16.000Z"
  },
  {
    "id": "6e7df9f1-9f3b-4078-9382-23a9c23d048b",
    "tagname": "nave havasc",
    "description": "A nave havasc is a keyword or term assigned to a piece of information",
    "posts_count": 0,
    "created_at": "2022-07-03T20:37:08.000Z"
  },
  {
    "id": "70922197-2d37-41c0-b224-1e9597751509",
    "tagname": "pass",
    "description": "A pass is a keyword or term assigned to a piece of information",
    "posts_count": 0,
    "created_at": "2022-07-13T06:59:15.000Z"
  },
  {
    "id": "73e6f426-76a7-4fc1-8440-5730f139426e",
    "tagname": "python java js c==",
    "description": "A python java js c== is a keyword or term assigned to a piece of information",
    "posts_count": 0,
    "created_at": "2022-05-14T19:03:31.000Z"
  },
  {
    "id": "7d817f79-39c2-44dd-b707-ce0ece130dad",
    "tagname": "javascript react.js",
    "description": "A javascript react.js is a keyword or term assigned to a piece of information",
    "posts_count": 0,
    "created_at": "2022-03-08T10:40:03.000Z"
  },
  {
    "id": "8db321e7-2120-433b-8c86-d34ccfba6c8f",
    "tagname": "dfsfdsf",
    "description": "A dfsfdsf is a keyword or term assigned to a piece of information",
    "posts_count": 0,
    "created_at": "2022-07-03T22:04:03.000Z"
  },
  {
    "id": "9504d3c9-24a6-4c60-8add-878db6e3801d",
    "tagname": "tag",
    "description": "A tag is a keyword or term assigned to a piece of information",
    "posts_count": 0,
    "created_at": "2022-07-04T21:56:07.000Z"
  },
  {
    "id": "a1bb3e5f-868b-4c62-b81b-97a9f245dc4e",
    "tagname": "clear",
    "description": "A clear is a keyword or term assigned to a piece of information",
    "posts_count": 0,
    "created_at": "2022-07-13T06:59:15.000Z"
  },
  {
    "id": "a37cb9c2-9f26-42af-8163-e060c84808b9",
    "tagname": "substring",
    "description": "Part of a string, or the function/method that returns part of a string",
    "posts_count": 0,
    "created_at": "2022-03-03T19:06:30.000Z"
  },
  {
    "id": "a9db8a77-46ce-43e0-b9d7-244008cbd105",
    "tagname": "eff",
    "description": "A eff is a keyword or term assigned to a piece of information",
    "posts_count": 0,
    "created_at": "2022-07-03T22:03:47.000Z"
  },
  {
    "id": "aac54b4d-04bd-4c4c-a323-1a925f3eee42",
    "tagname": "a",
    "description": "A a is a keyword or term assigned to a piece of information",
    "posts_count": 0,
    "created_at": "2022-07-03T20:36:51.000Z"
  },
  {
    "id": "ada3c9c9-a024-4c70-99b4-91f021d1bfe3",
    "tagname": "React xxx xx",
    "description": "A React xxx xx is a keyword or term assigned to a piece of information",
    "posts_count": 0,
    "created_at": "2022-04-06T00:46:25.000Z"
  },
  {
    "id": "c86b95c1-8633-498c-87ae-ebe36840c47a",
    "tagname": "dffs",
    "description": "A dffs is a keyword or term assigned to a piece of information",
    "posts_count": 0,
    "created_at": "2022-07-03T22:04:03.000Z"
  },
  {
    "id": "ca4da3b9-3658-4b83-a18c-c0ee43b74d6c",
    "tagname": "asd",
    "description": "A asd is a keyword or term assigned to a piece of information",
    "posts_count": 0,
    "created_at": "2022-07-04T21:56:59.000Z"
  },
  {
    "id": "d37af680-8e17-4c27-a772-7949e3aed9fa",
    "tagname": "ths",
    "description": "A ths is a keyword or term assigned to a piece of information",
    "posts_count": 0,
    "created_at": "2022-03-03T17:52:24.000Z"
  },
  {
    "id": "da37b3bd-ba83-4aec-88a3-7960426b646f",
    "tagname": "sequelize",
    "description": "A sequelize is a keyword or term assigned to a piece of information",
    "posts_count": 0,
    "created_at": "2022-03-05T17:03:34.000Z"
  },
  {
    "id": "efdfd93c-6040-4e4b-8e7e-267cffe4fa0c",
    "tagname": "jsavascript",
    "description": "A jsavascript is a keyword or term assigned to a piece of information",
    "posts_count": 0,
    "created_at": "2022-08-25T04:21:03.000Z"
  }
]